hltest/__init__.py
hltest/test.py
hltest-0.0.3.dist-info/METADATA
hltest-0.0.3.dist-info/WHEEL
hltest-0.0.3.dist-info/top_level.txt
hltest-0.0.3.dist-info/RECORD
