Metadata-Version: 2.1
Name: hltest
Version: 0.0.3
Summary: 测试版本
Home-page: https://github.com/
Author: GFF
Author-email: gaofeifei0619@163.com
License: MIT License
Platform: UNKNOWN
Classifier: Programming Language :: Python :: 3
Classifier: License :: OSI Approved :: MIT License
Classifier: Operating System :: OS Independent
